columngenerationsolverpy/__init__.py
columngenerationsolverpy/branching_scheme.py
columngenerationsolverpy/column_generation.py
columngenerationsolverpy/commons.py
columngenerationsolverpy-0.0.15.dist-info/LICENSE
columngenerationsolverpy-0.0.15.dist-info/METADATA
columngenerationsolverpy-0.0.15.dist-info/WHEEL
columngenerationsolverpy-0.0.15.dist-info/top_level.txt
columngenerationsolverpy-0.0.15.dist-info/RECORD
