Metadata-Version: 2.1
Name: columngenerationsolverpy
Version: 0.0.15
Summary: A solver based on Column Generation
Home-page: https://github.com/fontanf/columngenerationsolverpy
Author: Florian Fontan
Author-email: dev@florian-fontan.fr
License: UNKNOWN
Project-URL: Bug Tracker, https://github.com/fontanf/columngenerationsolverpy/issues
Platform: UNKNOWN
Classifier: Programming Language :: Python :: 3
Classifier: License :: OSI Approved :: MIT License
Classifier: Operating System :: OS Independent
Requires-Python: >=3.6
License-File: LICENSE
Requires-Dist: sortedcontainers
Requires-Dist: pulp
Requires-Dist: treesearchsolverpy (>=0.0.5)
